stmol/__init__.py
stmol/utils.py
stmol-0.0.9.dist-info/LICENSE
stmol-0.0.9.dist-info/METADATA
stmol-0.0.9.dist-info/WHEEL
stmol-0.0.9.dist-info/top_level.txt
stmol-0.0.9.dist-info/RECORD
