Metadata-Version: 2.1
Name: stmol
Version: 0.0.9
Summary: Streamlit component for molecular visualization
Home-page: https://github.com/napoles-uach/streamlit_3dmol
Author: Jose Manuel Napoles Duarte
Author-email: jnapoles@uach.mx
Requires-Python: >=3.6
License-File: LICENSE
